aiotraversal/__init__.py
aiotraversal/app.py
aiotraversal/cmd.py
aiotraversal/helpers.py
aiotraversal/logger.py
aiotraversal/middlewares.py
aiotraversal/sentry.py
aiotraversal/serve.py
aiotraversal/settings.py
aiotraversal/static.py
aiotraversal-0.10.0.dist-info/DESCRIPTION.rst
aiotraversal-0.10.0.dist-info/METADATA
aiotraversal-0.10.0.dist-info/RECORD
aiotraversal-0.10.0.dist-info/WHEEL
aiotraversal-0.10.0.dist-info/metadata.json
aiotraversal-0.10.0.dist-info/top_level.txt
