Metadata-Version: 2.0
Name: aiotraversal
Version: 0.10.0
Summary: Traversal based asyncronious web framework
Home-page: https://github.com/zzzsochi/aiotraversal
Author: Alexander Zelenyak
Author-email: zzz.sochi@gmail.com
License: UNKNOWN
Keywords: asyncio,aiohttp,traversal,pyramid
Platform: UNKNOWN
Classifier: License :: OSI Approved :: BSD License
Classifier: Operating System :: POSIX
Classifier: Programming Language :: Python :: 3.4
Classifier: Programming Language :: Python :: 3.5
Classifier: Topic :: Internet :: WWW/HTTP
Requires-Dist: aiohttp (>=2.0)
Requires-Dist: aiohttp-exc-handlers
Requires-Dist: aiohttp-traversal (>=0.9)
Requires-Dist: includer
Requires-Dist: resolver-deco
Requires-Dist: zini (>=1.0.2)
